pdf_table_extractor/__init__.py
pdf_table_extractor/cli.py
pdf_table_extractor/pdf_table_extractor.py
pdf_table_extractor-0.1.2.dist-info/DESCRIPTION.rst
pdf_table_extractor-0.1.2.dist-info/METADATA
pdf_table_extractor-0.1.2.dist-info/RECORD
pdf_table_extractor-0.1.2.dist-info/WHEEL
pdf_table_extractor-0.1.2.dist-info/entry_points.txt
pdf_table_extractor-0.1.2.dist-info/metadata.json
pdf_table_extractor-0.1.2.dist-info/top_level.txt
