Metadata-Version: 2.0
Name: pdf-table-extractor
Version: 0.1.2
Summary: Extract table data from PDFs
Home-page: https://github.com/mpasternak/pdf-table-extractor
Author: Michał Pasternak
Author-email: michal.dtz@gmail.com
License: MIT license
Keywords: pdf_table_extractor
Platform: UNKNOWN
Classifier: Development Status :: 2 - Pre-Alpha
Classifier: Intended Audience :: Developers
Classifier: License :: OSI Approved :: MIT License
Classifier: Natural Language :: English
Classifier: Programming Language :: Python :: 2
Classifier: Programming Language :: Python :: 2.7
Classifier: Programming Language :: Python :: 3
Classifier: Programming Language :: Python :: 3.6
Requires-Dist: Click (>=6.0)
Requires-Dist: drunken-child-in-the-fog (>=0.3.0)
Provides-Extra: xls
Requires-Dist: xlwt (==1.2.0); extra == 'xls'
